setup.py
mission_alert/__init__.py
mission_alert.egg-info/PKG-INFO
mission_alert.egg-info/SOURCES.txt
mission_alert.egg-info/dependency_links.txt
mission_alert.egg-info/entry_points.txt
mission_alert.egg-info/requires.txt
mission_alert.egg-info/top_level.txt