Metadata-Version: 1.0
Name: mission-alert
Version: 1.0.5
Summary: alert mission complete in server through email
Home-page: https://github.com/Xanxus1111
Author: xanxus
Author-email: 123@123.com
License: MIT
Platform: UNKNOWN
